pygsa/__init__.py
pygsa/constants.py
pygsa/draft.py
pygsa/saindices/__init__.py
pygsa/saindices/sobol_indices.py
pygsa/sampling/__init__.py
pygsa/sampling/directions.py
pygsa/sampling/sobol_sequence.py
pygsa-0.1.dist-info/LICENSE
pygsa-0.1.dist-info/METADATA
pygsa-0.1.dist-info/WHEEL
pygsa-0.1.dist-info/top_level.txt
pygsa-0.1.dist-info/RECORD
